py_solar_forecast/__init__.py
py_solar_forecast/exceptions.py
py_solar_forecast/models.py
py_solar_forecast/py.typed
py_solar_forecast/py_solar_forecast.py
py_solar_forecast-0.0.3.dist-info/LICENSE
py_solar_forecast-0.0.3.dist-info/METADATA
py_solar_forecast-0.0.3.dist-info/WHEEL
py_solar_forecast-0.0.3.dist-info/RECORD
