Metadata-Version: 2.1
Name: py-solar-forecast
Version: 0.0.3
Summary: Asynchronous Python client for getting forecast solar information
Home-page: https://github.com/rany2/py-solar-forecast
License: MIT
Keywords: forecast,solar,power,energy,api,async,client
Author: Klaas Schoute
Author-email: hello@student-techlife.com
Maintainer: Rany
Maintainer-email: rany@riseup.net
Requires-Python: >=3.11,<4.0
Classifier: Framework :: AsyncIO
Classifier: Intended Audience :: Developers
Classifier: License :: OSI Approved :: MIT License
Classifier: Natural Language :: English
Classifier: Programming Language :: Python :: 3
Classifier: Programming Language :: Python :: 3.11
Classifier: Programming Language :: Python :: 3.12
Classifier: Topic :: Software Development :: Libraries :: Python Modules
Requires-Dist: aiohttp (>=3.0.0)
Requires-Dist: yarl (>=1.6.0)
Project-URL: Bug Tracker, https://github.com/rany2/py-solar-forecast/issues
Project-URL: Changelog, https://github.com/rany2/py-solar-forecast/releases
Project-URL: Documentation, https://github.com/rany2/py-solar-forecast
Project-URL: Repository, https://github.com/rany2/py-solar-forecast
